CellPLM/__init__.py
CellPLM/decoder/__init__.py
CellPLM/decoder/mlp.py
CellPLM/decoder/zinb.py
CellPLM/embedder/__init__.py
CellPLM/embedder/omics.py
CellPLM/encoder/__init__.py
CellPLM/encoder/mlp.py
CellPLM/encoder/transformer.py
CellPLM/head/__init__.py
CellPLM/head/downstream.py
CellPLM/latent/__init__.py
CellPLM/latent/adversarial.py
CellPLM/latent/autoencoders.py
CellPLM/latent/contrastive.py
CellPLM/layer/__init__.py
CellPLM/layer/cosformer.py
CellPLM/layer/flowformer.py
CellPLM/layer/performer.py
CellPLM/layer/transformer.py
CellPLM/model/__init__.py
CellPLM/model/cellformer.py
CellPLM/objective/__init__.py
CellPLM/objective/autoencoder.py
CellPLM/objective/zinb.py
CellPLM/pipeline/__init__.py
CellPLM/pipeline/cell_embedding.py
CellPLM/pipeline/cell_type_annotation.py
CellPLM/pipeline/experimental.py
CellPLM/pipeline/imputation.py
CellPLM/utils/__init__.py
CellPLM/utils/data.py
CellPLM/utils/eval.py
CellPLM/utils/mask.py
CellPLM/utils/pe.py
CellPLM/utils/sparse.py
cellplm-0.1.0.post2.dist-info/LICENSE
cellplm-0.1.0.post2.dist-info/METADATA
cellplm-0.1.0.post2.dist-info/WHEEL
cellplm-0.1.0.post2.dist-info/top_level.txt
cellplm-0.1.0.post2.dist-info/RECORD
