Metadata-Version: 2.1
Name: cellplm
Version: 0.1.0.post2
Summary: Package of CellPLM: A pretrain-ed cell language model beyond single cells. Paper link: https://www.biorxiv.org/content/10.1101/2023.10.03.560734
Author-email: Hongzhi Wen <wenhongz@msu.edu>
Project-URL: Homepage, https://github.com/OmicsML/CellPLM
Project-URL: Issues, https://github.com/OmicsML/CellPLM/issues
Classifier: Programming Language :: Python :: 3
Classifier: License :: OSI Approved :: BSD License
Classifier: Operating System :: OS Independent
Classifier: Intended Audience :: Science/Research
Requires-Python: >=3.9
License-File: LICENSE
Requires-Dist: pydance
Requires-Dist: einops
Requires-Dist: torchmetrics
Requires-Dist: hdf5plugin
Requires-Dist: mygene
Provides-Extra: rapids
Requires-Dist: rapids-singlecell ; extra == 'rapids'
